{
  "playsByInning": [
    {
      "startIndex": 0,
      "endIndex": 6,
      "top": [0, 1, 2],
      "bottom": [3, 4, 5, 6],
      "hits": {
        "away": [
          {
            "team": {
              "springLeague": {
                "id": 114,
                "name": "Cactus League",
                "link": "/api/v1/league/114",
                "abbreviation": "CL"
              },
              "allStarStatus": "N",
              "id": 135,
              "name": "San Diego Padres",
              "link": "/api/v1/teams/135"
            },
            "inning": 1,
            "pitcher": {
              "id": 656427,
              "fullName": "Jack Flaherty",
              "link": "/api/v1/people/656427"
            },
            "batter": {
              "id": 592518,
              "fullName": "Manny Machado",
              "link": "/api/v1/people/592518"
            },
            "coordinates": { "x": 108.24, "y": 155.74 },
            "type": "O",
            "description": "Groundout"
          }
        ],
        "home": [
          {
            "team": {
              "springLeague": {
                "id": 115,
                "name": "Grapefruit League",
                "link": "/api/v1/league/115",
                "abbreviation": "GL"
              },
              "allStarStatus": "N",
              "id": 116,
              "name": "Detroit Tigers",
              "link": "/api/v1/teams/116"
            },
            "inning": 1,
            "pitcher": {
              "id": 601713,
              "fullName": "Nick Pivetta",
              "link": "/api/v1/people/601713"
            },
            "batter": {
              "id": 681481,
              "fullName": "Kerry Carpenter",
              "link": "/api/v1/people/681481"
            },
            "coordinates": { "x": 136.71, "y": 182.38 },
            "type": "O",
            "description": "Groundout"
          },
          {
            "team": {
              "springLeague": {
                "id": 115,
                "name": "Grapefruit League",
                "link": "/api/v1/league/115",
                "abbreviation": "GL"
              },
              "allStarStatus": "N",
              "id": 116,
              "name": "Detroit Tigers",
              "link": "/api/v1/teams/116"
            },
            "inning": 1,
            "pitcher": {
              "id": 601713,
              "fullName": "Nick Pivetta",
              "link": "/api/v1/people/601713"
            },
            "batter": {
              "id": 679529,
              "fullName": "Spencer Torkelson",
              "link": "/api/v1/people/679529"
            },
            "coordinates": { "x": 180.1, "y": 150.16 },
            "type": "O",
            "description": "Pop Out"
          }
        ]
      }
    },
    {
      "startIndex": 7,
      "endIndex": 15,
      "top": [7, 8, 9, 10, 11],
      "bottom": [12, 13, 14, 15],
      "hits": {
        "away": [
          {
            "team": {
              "springLeague": {
                "id": 114,
                "name": "Cactus League",
                "link": "/api/v1/league/114",
                "abbreviation": "CL"
              },
              "allStarStatus": "N",
              "id": 135,
              "name": "San Diego Padres",
              "link": "/api/v1/teams/135"
            },
            "inning": 2,
            "pitcher": {
              "id": 656427,
              "fullName": "Jack Flaherty",
              "link": "/api/v1/people/656427"
            },
            "batter": {
              "id": 593428,
              "fullName": "Xander Bogaerts",
              "link": "/api/v1/people/593428"
            },
            "coordinates": { "x": 94.1, "y": 165.18 },
            "type": "H",
            "description": "Single"
          },
          {
            "team": {
              "springLeague": {
                "id": 114,
                "name": "Cactus League",
                "link": "/api/v1/league/114",
                "abbreviation": "CL"
              },
              "allStarStatus": "N",
              "id": 135,
              "name": "San Diego Padres",
              "link": "/api/v1/teams/135"
            },
            "inning": 2,
            "pitcher": {
              "id": 656427,
              "fullName": "Jack Flaherty",
              "link": "/api/v1/people/656427"
            },
            "batter": {
              "id": 553869,
              "fullName": "Elias Díaz",
              "link": "/api/v1/people/553869"
            },
            "coordinates": { "x": 38.24, "y": 86.48 },
            "type": "H",
            "description": "Home Run"
          }
        ],
        "home": [
          {
            "team": {
              "springLeague": {
                "id": 115,
                "name": "Grapefruit League",
                "link": "/api/v1/league/115",
                "abbreviation": "GL"
              },
              "allStarStatus": "N",
              "id": 116,
              "name": "Detroit Tigers",
              "link": "/api/v1/teams/116"
            },
            "inning": 2,
            "pitcher": {
              "id": 601713,
              "fullName": "Nick Pivetta",
              "link": "/api/v1/people/601713"
            },
            "batter": {
              "id": 669234,
              "fullName": "Justyn-Henry Malloy",
              "link": "/api/v1/people/669234"
            },
            "coordinates": { "x": 141.32, "y": 71.76 },
            "type": "O",
            "description": "Lineout"
          },
          {
            "team": {
              "springLeague": {
                "id": 115,
                "name": "Grapefruit League",
                "link": "/api/v1/league/115",
                "abbreviation": "GL"
              },
              "allStarStatus": "N",
              "id": 116,
              "name": "Detroit Tigers",
              "link": "/api/v1/teams/116"
            },
            "inning": 2,
            "pitcher": {
              "id": 601713,
              "fullName": "Nick Pivetta",
              "link": "/api/v1/people/601713"
            },
            "batter": {
              "id": 693307,
              "fullName": "Dillon Dingler",
              "link": "/api/v1/people/693307"
            },
            "coordinates": { "x": 123.95, "y": 81.75 },
            "type": "H",
            "description": "Single"
          },
          {
            "team": {
              "springLeague": {
                "id": 115,
                "name": "Grapefruit League",
                "link": "/api/v1/league/115",
                "abbreviation": "GL"
              },
              "allStarStatus": "N",
              "id": 116,
              "name": "Detroit Tigers",
              "link": "/api/v1/teams/116"
            },
            "inning": 2,
            "pitcher": {
              "id": 601713,
              "fullName": "Nick Pivetta",
              "link": "/api/v1/people/601713"
            },
            "batter": {
              "id": 700242,
              "fullName": "Trey Sweeney",
              "link": "/api/v1/people/700242"
            },
            "coordinates": { "x": 160.94, "y": 73.69 },
            "type": "O",
            "description": "Flyout"
          }
        ]
      }
    },
    {
      "startIndex": 16,
      "endIndex": 19,
      "top": [16, 17, 18, 19],
      "bottom": [],
      "hits": {
        "away": [
          {
            "team": {
              "springLeague": {
                "id": 114,
                "name": "Cactus League",
                "link": "/api/v1/league/114",
                "abbreviation": "CL"
              },
              "allStarStatus": "N",
              "id": 135,
              "name": "San Diego Padres",
              "link": "/api/v1/teams/135"
            },
            "inning": 3,
            "pitcher": {
              "id": 656427,
              "fullName": "Jack Flaherty",
              "link": "/api/v1/people/656427"
            },
            "batter": {
              "id": 669200,
              "fullName": "Mason McCoy",
              "link": "/api/v1/people/669200"
            },
            "coordinates": { "x": 132.08, "y": 142.05 },
            "type": "O",
            "description": "Groundout"
          },
          {
            "team": {
              "springLeague": {
                "id": 114,
                "name": "Cactus League",
                "link": "/api/v1/league/114",
                "abbreviation": "CL"
              },
              "allStarStatus": "N",
              "id": 135,
              "name": "San Diego Padres",
              "link": "/api/v1/teams/135"
            },
            "inning": 3,
            "pitcher": {
              "id": 656427,
              "fullName": "Jack Flaherty",
              "link": "/api/v1/people/656427"
            },
            "batter": {
              "id": 665487,
              "fullName": "Fernando Tatis Jr.",
              "link": "/api/v1/people/665487"
            },
            "coordinates": { "x": 113.3, "y": 152.19 },
            "type": "E",
            "description": "Field Error"
          }
        ],
        "home": []
      }
    }
  ]
}
